mpypack/__init__.py
mpypack/cli.py
mpypack/fileexplorer.py
mpypack/filesync.py
mpypack/mpycross.py
mpypack/pyboard.py
mpypack/version.py
mpypack-0.1.8.dist-info/LICENSE
mpypack-0.1.8.dist-info/METADATA
mpypack-0.1.8.dist-info/WHEEL
mpypack-0.1.8.dist-info/entry_points.txt
mpypack-0.1.8.dist-info/top_level.txt
mpypack-0.1.8.dist-info/RECORD
