Metadata-Version: 2.1
Name: mpypack
Version: 0.1.8
Summary: A simple tool to pack up MicroPython code 
Home-page: https://github.com/dreagonmon/mpypack
Author: Dreagonmon
Author-email: 531486058@qq.com
License: UNKNOWN
Keywords: micropython,file transfer,development
Platform: UNKNOWN
Classifier: Programming Language :: Python :: 3
Classifier: License :: OSI Approved :: MIT License
Requires-Python: >=3.6
License-File: LICENSE
Requires-Dist: pyserial
Requires-Dist: mpy-cross
Requires-Dist: click
